CHANGELOG.md
scengen/__init__.py
scengen/__main__.py
scengen/cli.py
scengen/estimator.py
scengen/evaluator.py
scengen/files.py
scengen/generation/__init__.py
scengen/generation/check.py
scengen/generation/digest.py
scengen/generation/generator.py
scengen/generation/misc.py
scengen/logs.py
scengen/runner.py
scengen/workflow.py
amiris_scengen-1.1.1.dist-info/entry_points.txt
amiris_scengen-1.1.1.dist-info/LICENSES/Apache-2.0.txt
amiris_scengen-1.1.1.dist-info/LICENSES/CC-BY-4.0.txt
amiris_scengen-1.1.1.dist-info/LICENSES/CC0-1.0.txt
amiris_scengen-1.1.1.dist-info/METADATA
amiris_scengen-1.1.1.dist-info/WHEEL
amiris_scengen-1.1.1.dist-info/RECORD
