Metadata-Version: 2.1
Name: amiris-scengen
Version: 1.1.1
Summary: Scenario generator for the open electricity market model AMIRIS
Home-page: https://gitlab.com/dlr-ve/esy/amiris/
License: Apache-2.0
Keywords: scenario,generator,AMIRIS,agent-based modelling,electricity market,simulation
Author: Felix Nitsch
Author-email: amiris@dlr.de
Maintainer: Felix Nitsch
Maintainer-email: amiris@dlr.de
Requires-Python: >=3.9,<4.0
Classifier: Development Status :: 5 - Production/Stable
Classifier: Environment :: Console
Classifier: Intended Audience :: Science/Research
Classifier: License :: OSI Approved :: Apache Software License
Classifier: Operating System :: OS Independent
Classifier: Programming Language :: Python :: 3
Classifier: Programming Language :: Python :: 3.9
Classifier: Programming Language :: Python :: 3.10
Classifier: Programming Language :: Python :: 3.11
Classifier: Programming Language :: Python :: 3.12
Classifier: Topic :: Scientific/Engineering
Requires-Dist: amirispy (>=3.0,<4.0)
Requires-Dist: pandas (>=2.0,<3.0)
Project-URL: Repository, https://gitlab.com/dlr-ve/esy/amiris/amiris-scengen
